namefiles.py
namefiles-0.6.0.dist-info/LICENSE.md
namefiles-0.6.0.dist-info/METADATA
namefiles-0.6.0.dist-info/WHEEL
namefiles-0.6.0.dist-info/top_level.txt
namefiles-0.6.0.dist-info/RECORD
