Metadata-Version: 2.1
Name: namefiles
Version: 0.6.0
Summary: Standard naming convention for filenames to distinguish multiple files of an entity.
Home-page: https://https://gitlab.com/david.scheliga/namefiles
Author: David Scheliga
License: GNU General Public License V3 (GPLv3)
Project-URL: Documentation, https://namefiles.readthedocs.io/en/latest/
Project-URL: Source Code Repository, https://https://gitlab.com/david.scheliga/namefiles
Platform: UNKNOWN
Classifier: Development Status :: 5 - Production/Stable
Classifier: License :: OSI Approved :: GNU General Public License v3 (GPLv3)
Classifier: Operating System :: OS Independent
Classifier: Programming Language :: Python :: 3
Classifier: Programming Language :: Python :: 3.6
Classifier: Programming Language :: Python :: 3.7
Classifier: Programming Language :: Python :: 3.8
Classifier: Programming Language :: Python :: 3.9
Requires-Dist: jsonschema
